bdtemplater/__init__.py
bdtemplater/bdtemplatize.py
bdtemplaterexample/__init__.py
bdtemplaterexample/example_post_process.py
bdtemplaterpostprocessor/__init__.py
bdtemplaterpostprocessor/default_post_process.py
bdtemplater-0.11.1.dist-info/METADATA
bdtemplater-0.11.1.dist-info/WHEEL
bdtemplater-0.11.1.dist-info/entry_points.txt
bdtemplater-0.11.1.dist-info/licenses/LICENSE
bdtemplater-0.11.1.dist-info/RECORD
