Metadata-Version: 2.4
Name: bdtemplater
Version: 0.11.1
Summary: A utility for generating templates in a mostly brain-dead way
Project-URL: Homepage, https://github.com/infrastructurebuilder/bdtemplater
Project-URL: Repository, https://github.com/infrastructurebuilder/bdtemplater
Project-URL: Issues, https://github.com/infrastructurebuilder/bdtemplater/issues
Author-email: Mykel Alvis <mykel.alvis@gmail.com>
License: Apache-2.0
License-File: LICENSE
Classifier: Development Status :: 3 - Alpha
Classifier: Intended Audience :: Developers
Classifier: License :: OSI Approved :: Apache Software License
Classifier: Programming Language :: Python :: 3
Classifier: Programming Language :: Python :: 3.8
Classifier: Programming Language :: Python :: 3.9
Classifier: Programming Language :: Python :: 3.10
Classifier: Programming Language :: Python :: 3.11
Classifier: Programming Language :: Python :: 3.12
Classifier: Topic :: Software Development :: Code Generators
Classifier: Topic :: System :: Systems Administration
Requires-Python: >=3.8
